LICENSE
MANIFEST.in
README.md
README.rst
setup.py
iou/__init__.py
iou/httpreactor.py
iou/iou.py
iou/iou_reactor_base.py
iou.egg-info/PKG-INFO
iou.egg-info/SOURCES.txt
iou.egg-info/dependency_links.txt
iou.egg-info/requires.txt
iou.egg-info/top_level.txt