Metadata-Version: 1.1
Name: iou
Version: 0.1.0
Summary: Promise-like data encapsulation for asynchronous behavior
Home-page: https://github.com/reinecke/IOU
Author: Eric Reinecke
Author-email: reinecke.eric@gmail.com
License: MIT
Platform: UNKNOWN
Classifier: Intended Audience :: Developers
Classifier: Natural Language :: English
Classifier: License :: OSI Approved :: MIT License
Classifier: Operating System :: OS Independent
Classifier: Programming Language :: Python
Classifier: Programming Language :: Python :: 2
